pgamit/ConvertRaw.py
pgamit/StationList.py
pgamit/Utils.py
pgamit/__init__.py
pgamit/agglomerative.py
pgamit/cluster.py
pgamit/dbConnection.py
pgamit/dbConnection_old.py
pgamit/igslog.py
pgamit/network.py
pgamit/plots.py
pgamit/proto_download.py
pgamit/pyArchiveStruct.py
pgamit/pyBunch.py
pgamit/pyDate.py
pgamit/pyETM.py
pgamit/pyEvents.py
pgamit/pyGamitConfig.py
pgamit/pyGamitSession.py
pgamit/pyGamitTask.py
pgamit/pyGlobkTask.py
pgamit/pyJobServer.py
pgamit/pyLeastSquares.py
pgamit/pyOTL.py
pgamit/pyOkada.py
pgamit/pyOptions.py
pgamit/pyPPP.py
pgamit/pyParseAntex.py
pgamit/pyParseZTD.py
pgamit/pyProducts.py
pgamit/pyRinex.py
pgamit/pyRinexName.py
pgamit/pyRunWithRetry.py
pgamit/pyStack.py
pgamit/pyStatic1d.py
pgamit/pyStation.py
pgamit/pyStationInfo.py
pgamit/pyTerminal.py
pgamit/pyVoronoi.py
pgamit/pyZTD.py
pgamit/snxParse.py
pgamit/.idea/classes.iml
pgamit/.idea/encodings.xml
pgamit/.idea/misc.xml
pgamit/.idea/modules.xml
pgamit/.idea/vcs.xml
pgamit/.idea/workspace.xml
pgamit/tests/__init__.py
pgamit/tests/common.py
pgamit/tests/test_make_clusters.py
pgamit/tests/test_version.py
pgamit-1.2.47.data/scripts/AlterETM.py
pgamit-1.2.47.data/scripts/ArchiveService.py
pgamit-1.2.47.data/scripts/CloseStationInfo.py
pgamit-1.2.47.data/scripts/ConvertDate.py
pgamit-1.2.47.data/scripts/ConvertTrimble.py
pgamit-1.2.47.data/scripts/DRA.py
pgamit-1.2.47.data/scripts/DownloadSources.py
pgamit-1.2.47.data/scripts/DownloadSourcesFill.py
pgamit-1.2.47.data/scripts/FixPlate.py
pgamit-1.2.47.data/scripts/GenerateKml.py
pgamit-1.2.47.data/scripts/GenerateSinex.py
pgamit-1.2.47.data/scripts/IntegrityCheck.py
pgamit-1.2.47.data/scripts/LocateRinex.py
pgamit-1.2.47.data/scripts/ModelProcessing.py
pgamit-1.2.47.data/scripts/NEQStack.py
pgamit-1.2.47.data/scripts/OTL_FES2014b.py
pgamit-1.2.47.data/scripts/ParallelGamit.py
pgamit-1.2.47.data/scripts/PlotETM.py
pgamit-1.2.47.data/scripts/PlotMapView.py
pgamit-1.2.47.data/scripts/QueryETM.py
pgamit-1.2.47.data/scripts/S-score.py
pgamit-1.2.47.dist-info/licenses/LICENSE
pgamit-1.2.47.dist-info/METADATA
pgamit-1.2.47.dist-info/WHEEL
pgamit-1.2.47.dist-info/top_level.txt
pgamit-1.2.47.dist-info/RECORD
