Metadata-Version: 2.4
Name: pgamit
Version: 1.2.47
Summary: A Python wrapper to parallelize GAMIT executions
Home-page: https://github.com/demiangomez/Parallel.GAMIT
Author: Demián D. Gómez
Author-email: "Demián D. Gómez" <demiang@gmail.com>
Maintainer-email: "Demián D. Gómez" <demiang@gmail.com>, "Shane Grigsby (espg)" <refuge@rocktalus.com>
License: BSD 3-Clause License
Project-URL: Homepage, https://github.com/demiangomez/Parallel.GAMIT
Project-URL: Bug Tracker, https://github.com/demiangomez/Parallel.GAMIT/issues
Keywords: GAMIT
Classifier: Programming Language :: Python :: 3
Classifier: License :: OSI Approved :: MIT License
Classifier: Operating System :: OS Independent
Requires-Python: >=3.10
License-File: LICENSE
Requires-Dist: numpy==1.26.4
Requires-Dist: pandas
Requires-Dist: tqdm==4.66.5
Requires-Dist: dispy
Requires-Dist: psycopg2-binary==2.9.9
Requires-Dist: pycos
Requires-Dist: country-converter
Requires-Dist: earthscope-cli==0.8.2
Requires-Dist: earthscope-sdk==0.2.0
Requires-Dist: basemap==1.4.0
Requires-Dist: cryptography==44.0.1
Requires-Dist: dirsync>=2.2.4
Requires-Dist: geopy==2.4.1
Requires-Dist: usgs-libcomcat
Requires-Dist: matplotlib>=2.0.0
Requires-Dist: munch==2.5.0
Requires-Dist: netifaces==0.10.9
Requires-Dist: networkx
Requires-Dist: paramiko==3.4.0
Requires-Dist: psutil>=5.6.3
Requires-Dist: pysftp==0.2.9
Requires-Dist: requests==2.32.4
Requires-Dist: scandir>=1.6
Requires-Dist: scikit-learn>=1.1
Requires-Dist: scipy>=1.2.0
Requires-Dist: simplekml==1.3.6
Requires-Dist: xmltodict==0.13.0
Requires-Dist: scikit-image
Requires-Dist: shapely
Requires-Dist: obspy
Dynamic: license-file
